minimal_shared_kmers/__init__.py
minimal_shared_kmers/kmer_frequency_distribution_mini_shared.py
minimal_shared_kmers-0.1.1.dist-info/LICENSE
minimal_shared_kmers-0.1.1.dist-info/METADATA
minimal_shared_kmers-0.1.1.dist-info/WHEEL
minimal_shared_kmers-0.1.1.dist-info/entry_points.txt
minimal_shared_kmers-0.1.1.dist-info/top_level.txt
minimal_shared_kmers-0.1.1.dist-info/RECORD
