Metadata-Version: 2.1
Name: minimal_shared_kmers
Version: 0.1.1
Summary: minimal shared K-mers across the whole transcriptome
Home-page: https://github.com/QiangSu/GaussF
Author: Qiang Su
Author-email: qiang_su@hotmail.com
Classifier: Programming Language :: Python :: 3
Classifier: License :: OSI Approved :: MIT License
Classifier: Operating System :: OS Independent
Requires-Python: >=3.6
License-File: LICENSE
